CONTRIBUTING.rst
HISTORY.rst
LICENSE
MANIFEST.in
README.rst
setup.cfg
setup.py
docs/Makefile
docs/conf.py
docs/contributing.rst
docs/gadget.rst
docs/history.rst
docs/index.rst
docs/installation.rst
docs/make.bat
docs/modules.rst
docs/overview.rst
docs/usage.rst
gadget/__init__.py
gadget/__version__.py
gadget/gadget_python.py
gadget_python.egg-info/PKG-INFO
gadget_python.egg-info/SOURCES.txt
gadget_python.egg-info/dependency_links.txt
gadget_python.egg-info/not-zip-safe
gadget_python.egg-info/requires.txt
gadget_python.egg-info/top_level.txt
tests/__init__.py
tests/test_gadget.py
tests/test_parsing.py