Metadata-Version: 1.1
Name: gadget-python
Version: 0.2.1
Summary: Python utilities for emitting and processing Gadget log entries
Home-page: https://github.com/getslash/gadget-python
Author: Slash Team
Author-email: vmalloc@gmail.com
License: MIT license
Keywords: gadget_python
Platform: UNKNOWN
Classifier: Development Status :: 2 - Pre-Alpha
Classifier: Intended Audience :: Developers
Classifier: License :: OSI Approved :: MIT License
Classifier: Natural Language :: English
Classifier: Programming Language :: Python :: 2
Classifier: Programming Language :: Python :: 2.6
Classifier: Programming Language :: Python :: 2.7
Classifier: Programming Language :: Python :: 3
Classifier: Programming Language :: Python :: 3.3
Classifier: Programming Language :: Python :: 3.4
Classifier: Programming Language :: Python :: 3.5
